MatterPy/__init__.py
MatterPy/main.py
MatterPy-0.0.5.dist-info/LICENSE
MatterPy-0.0.5.dist-info/METADATA
MatterPy-0.0.5.dist-info/WHEEL
MatterPy-0.0.5.dist-info/top_level.txt
MatterPy-0.0.5.dist-info/RECORD
