Metadata-Version: 2.1
Name: MatterPy
Version: 0.0.5
Summary: A Python library that deals with properties of matter.
Home-page: https://github.com/PyndyalaCoder/MatterPy
Author: Siddhu Pendyala
Author-email: elcientifico.pendyala@gmail.com
License: MIT
Project-URL: Bug Tracker, https://github.com/PyndyalaCoder/MatterPy/issues
License-File: LICENSE
Requires-Dist: requests
